{
  "OrderNumber": "JUDGEDOC2019071914311897035932",
  "Paging": {
    "PageSize": 10,
    "PageIndex": 1,
    "TotalRecords": 30
  },
  "Result": [
    {
      "Id": "eb3401516af899980e63f897880cfb9e",
      "Court": "重庆市渝北区人民法院",
      "CaseName": "黎江军与上海元祖梦果子股份有限公司重庆爱立达科技有限公司产品责任纠纷一审民事裁定书",
      "CaseNo": "（2019）渝0112民初13222号",
      "CaseType": "ms",
      "SubmitDate": "2019-07-10 00:00:00",
      "UpdateDate": "2019-07-02 00:00:00",
      "IsProsecutor": false,
      "IsDefendant": true,
      "CourtYear": "2019",
      "CaseRole": "[{\"P\":\"黎江军\",\"R\":\"原告\"},{\"P\":\"重庆爱立达科技有限公司\",\"R\":\"被告\"},{\"P\":\"上海元祖梦果子股份有限公司\",\"R\":\"被告\"}]",
      "CourtLevel": "2",
      "CaseReason": "产品责任纠纷",
      "CaseReasonType": "0071",
      "CourtMonth": "201907"
    },
    {
      "Id": "469ccdeefa5cbeabdbb227c3bb1f78d8",
      "Court": "上海市青浦区人民法院",
      "CaseName": "顾美燕与上海元祖梦果子股份有限公司劳动合同纠纷一审民事判决书",
      "CaseNo": "（2018）沪0118民初8712号",
      "CaseType": "ms",
      "SubmitDate": "2019-02-18 00:00:00",
      "UpdateDate": "2018-08-28 00:00:00",
      "IsProsecutor": false,
      "IsDefendant": true,
      "CourtYear": "2019",
      "CaseRole": "[{\"P\":\"顾美燕\",\"R\":\"原告\"},{\"P\":\"上海元祖梦果子股份有限公司\",\"R\":\"被告\"}]",
      "CourtLevel": "2",
      "CaseReason": "劳动合同纠纷",
      "CaseReasonType": "0032",
      "CourtMonth": "201902"
    },
    {
      "Id": "65496edd784174f498f143648ffef24a",
      "Court": "上海市第二中级人民法院",
      "CaseName": "上海元祖梦果子股份有限公司与上海同济室内设计工程有限公司装饰装修合同纠纷二审民事判决书",
      "CaseNo": "（2018）沪02民终5727号",
      "CaseType": "ms",
      "SubmitDate": "2018-08-06 00:00:00",
      "UpdateDate": "2018-07-25 00:00:00",
      "IsProsecutor": true,
      "IsDefendant": false,
      "CourtYear": "2018",
      "CaseRole": "[{\"P\":\"上海元祖梦果子股份有限公司\",\"R\":\"上诉人(原审被告)\"},{\"P\":\"上海市方正律师事务所\",\"R\":\"代理律师事务所\"},{\"P\":\"上海同济室内设计工程有限公司\",\"R\":\"被上诉人(原审原告)\"},{\"P\":\"上海市凤凰律师事务所\",\"R\":\"代理律师事务所\"}]",
      "CourtLevel": "3",
      "CaseReason": "装饰装修合同纠纷",
      "CaseReasonType": "0061",
      "CourtMonth": "201808"
    },
    {
      "Id": "b77736e5c14adb960866b8c79669068e",
      "Court": "上海市青浦区人民法院",
      "CaseName": "上海同济室内设计工程有限公司与上海元祖梦果子股份有限公司装饰装修合同纠纷一审民事判决书",
      "CaseNo": "（2017）沪0118民初4028号",
      "CaseType": "ms",
      "SubmitDate": "2018-08-06 00:00:00",
      "UpdateDate": "2018-03-30 00:00:00",
      "IsProsecutor": false,
      "IsDefendant": true,
      "CourtYear": "2018",
      "CaseRole": "[{\"P\":\"上海同济室内设计工程有限公司\",\"R\":\"原告\"},{\"P\":\"上海市凤凰律师事务所\",\"R\":\"代理律师事务所\"},{\"P\":\"上海元祖梦果子股份有限公司\",\"R\":\"被告\"},{\"P\":\"上海市方正律师事务所\",\"R\":\"代理律师事务所\"}]",
      "CourtLevel": "2",
      "CaseReason": "装饰装修合同纠纷",
      "CaseReasonType": "0061",
      "CourtMonth": "201808"
    },
    {
      "Id": "6a52cd5c3e37d06c71573d0d8d932f7b",
      "Court": "上海市青浦区人民法院",
      "CaseName": "上海元祖梦果子股份有限公司与上海同济室内设计工程有限公司建设工程施工合同纠纷一审民事裁定书",
      "CaseNo": "（2017）沪0118民初3664号",
      "CaseType": "ms",
      "SubmitDate": "2018-06-29 00:00:00",
      "UpdateDate": "2017-10-20 00:00:00",
      "IsProsecutor": true,
      "IsDefendant": false,
      "CourtYear": "2018",
      "CaseRole": "[{\"P\":\"上海元祖梦果子股份有限公司\",\"R\":\"原告\"},{\"P\":\"上海市方正律师事务所\",\"R\":\"代理律师事务所\"},{\"P\":\"上海同济室内设计工程有限公司\",\"R\":\"被告\"},{\"P\":\"上海市凤凰律师事务所\",\"R\":\"代理律师事务所\"}]",
      "CourtLevel": "2",
      "CaseReason": "建设工程施工合同纠纷",
      "CaseReasonType": "0018",
      "CourtMonth": "201806"
    },
    {
      "Id": "df63891ba1d4bdb3de51e51abad4909c",
      "Court": "上海市第一中级人民法院",
      "CaseName": "上海元祖梦果子股份有限公司诉上海人言投资管理有限公司房屋租赁合同纠纷一案二审民事判决书",
      "CaseNo": "（2017）沪01民终11884号",
      "CaseType": "ms",
      "SubmitDate": "2018-01-02 08:00:00",
      "UpdateDate": "2017-11-16 08:00:00",
      "IsProsecutor": true,
      "IsDefendant": false,
      "CourtYear": "2018",
      "CaseRole": "[{\"P\":\"上海元祖梦果子股份有限公司\",\"R\":\"上诉人（原审原告）\"},{\"P\":\"上海人言投资管理有限公司\",\"R\":\"被上诉人（原审被告）\"},{\"P\":\"上海市郑传本律师事务所\",\"R\":\"代理律师事务所\"}]",
      "CourtLevel": "3",
      "CaseReason": "房屋租赁合同纠纷",
      "CaseReasonType": "0019",
      "CourtMonth": "201801"
    },
    {
      "Id": "82185851c6fd580e16766239af63e79a",
      "Court": "上海市金山区人民法院",
      "CaseName": "原告上海元祖梦果子股份有限公司诉被告上海人言投资管理有限公司房屋租赁合同纠纷一审民事判决书",
      "CaseNo": "（2017）沪0116民初7117号",
      "CaseType": "ms",
      "SubmitDate": "2018-01-02 08:00:00",
      "UpdateDate": "2017-07-26 08:00:00",
      "IsProsecutor": true,
      "IsDefendant": false,
      "CourtYear": "2018",
      "CaseRole": "[{\"P\":\"上海元祖梦果子股份有限公司\",\"R\":\"原告\"},{\"P\":\"上海人言投资管理有限公司\",\"R\":\"被告\"},{\"P\":\"上海市郑传本律师事务所\",\"R\":\"代理律师事务所\"}]",
      "CourtLevel": "2",
      "CaseReason": "房屋租赁合同纠纷",
      "CaseReasonType": "0019",
      "CourtMonth": "201801"
    },
    {
      "Id": "d51670c54a92a0fa3766a5f4e55e305d",
      "Court": "北京知识产权法院",
      "CaseName": "网尚世界（北京）数字电影文化发展有限公司与国家工商行政管理总局商标评审委员会其他一案一审行政判决书",
      "CaseNo": "（2015）京知行初字第4547号",
      "CaseType": "xz",
      "SubmitDate": "2017-08-14 08:00:00",
      "UpdateDate": "2015-12-28 08:00:00",
      "IsProsecutor": false,
      "IsDefendant": true,
      "CourtYear": "2017",
      "CaseRole": "[{\"P\":\"网尚世界（北京）数字电影文化发展有限公司\",\"R\":\"原告\"},{\"P\":\"北京市中银律师事务所\",\"R\":\"代理律师事务所\"},{\"P\":\"国家工商行政管理总局商标评审委员会\",\"R\":\"被告\"},{\"P\":\"上海元祖梦果子股份有限公司\",\"R\":\"第三人\"},{\"P\":\"上海市光明律师事务所\",\"R\":\"代理律师事务所\"}]",
      "CourtLevel": "1",
      "CaseReason": "工商行政管理纠纷",
      "CaseReasonType": "0120",
      "CourtMonth": "201708"
    },
    {
      "Id": "2b6722bed473bb7d9b5df83c9d025437",
      "Court": "北京知识产权法院",
      "CaseName": "网尚世界（北京）数字电影文化发展有限公司诉国家工商行政管理总局商标评审委员会其他一案一审行政判决书",
      "CaseNo": "2015年京知行初字第04547号",
      "CaseType": "xz",
      "SubmitDate": "2017-08-11 00:00:00",
      "UpdateDate": "2015-12-28 00:00:00",
      "IsProsecutor": false,
      "IsDefendant": true,
      "CourtYear": "2017",
      "CaseRole": "[{\"P\":\"网尚世界（北京）数字电影文化发展有限公司\",\"R\":\"原告\"},{\"P\":\"北京市中银律师事务所\",\"R\":\"代理律师事务所\"},{\"P\":\"国家工商行政管理总局商标评审委员会\",\"R\":\"被告\"},{\"P\":\"上海元祖梦果子股份有限公司\",\"R\":\"第三人\"},{\"P\":\"上海市光明律师事务所\",\"R\":\"代理律师事务所\"}]",
      "CourtLevel": "1",
      "CaseReason": "其它类型纠纷",
      "CaseReasonType": "0456",
      "CourtMonth": "201708"
    },
    {
      "Id": "d857621bc3cba6ba7c17b1721e3e4532",
      "Court": "上海市第二中级人民法院",
      "CaseName": "上海元祖梦果子股份有限公司与上海天岳广告有限公司承揽合同纠纷二审民事判决书",
      "CaseNo": "（2017）沪02民终4570号",
      "CaseType": "ms",
      "SubmitDate": "2017-06-22 08:00:00",
      "UpdateDate": "2017-05-26 08:00:00",
      "IsProsecutor": true,
      "IsDefendant": false,
      "CourtYear": "2017",
      "CaseRole": "[{\"P\":\"上海元祖梦果子股份有限公司\",\"R\":\"上诉人（原审被告）\"},{\"P\":\"上海天岳广告有限公司\",\"R\":\"被上诉人（原审原告）\"}]",
      "CourtLevel": "3",
      "CaseReason": "承揽合同纠纷",
      "CaseReasonType": "0027",
      "CourtMonth": "201706"
    }
  ],
  "Status": "200",
  "Message": "查询成功"
}